[
  {
    "name": "a020_th60",
    "params": {
      "n_exc": 800,
      "n_per_class": 450,
      "epochs": 8,
      "T": 350,
      "a_plus": 0.02,
      "a_minus": 0.012,
      "norm_target": 90.0,
      "w_inh": 0.6,
      "theta_plus": 0.6,
      "r_m": 6.0,
      "input_norm_power": 0.5,
      "batch": 128,
      "max_rate": 63.75
    },
    "acc": 0.546,
    "tmpl_match": 0.5055424351831106,
    "tv": 1.1394434432685374,
    "dead": 0.13375,
    "cov_spread": 8.541666666666666,
    "n_zero_classes": 0,
    "sec": 1649.1232204437256,
    "n_train": 4500,
    "presentations": 36000
  },
  {
    "name": "a020_th80",
    "params": {
      "n_exc": 800,
      "n_per_class": 450,
      "epochs": 8,
      "T": 350,
      "a_plus": 0.02,
      "a_minus": 0.012,
      "norm_target": 90.0,
      "w_inh": 0.6,
      "theta_plus": 0.8,
      "r_m": 6.0,
      "input_norm_power": 0.5,
      "batch": 128,
      "max_rate": 63.75
    },
    "acc": 0.5513333333333333,
    "tmpl_match": 0.5878951798408475,
    "tv": 1.0746946115791798,
    "dead": 0.0825,
    "cov_spread": 6.035714285714286,
    "n_zero_classes": 0,
    "sec": 1648.3160707950592,
    "n_train": 4500,
    "presentations": 36000
  },
  {
    "name": "a020_th120",
    "params": {
      "n_exc": 800,
      "n_per_class": 450,
      "epochs": 8,
      "T": 350,
      "a_plus": 0.02,
      "a_minus": 0.012,
      "norm_target": 90.0,
      "w_inh": 0.6,
      "theta_plus": 1.2,
      "r_m": 6.0,
      "input_norm_power": 0.5,
      "batch": 128,
      "max_rate": 63.75
    },
    "acc": 0.6033333333333334,
    "tmpl_match": 0.7212757991227238,
    "tv": 0.9783502472192049,
    "dead": 0.01375,
    "cov_spread": 3.6285714285714286,
    "n_zero_classes": 0,
    "sec": 1646.6840381622314,
    "n_train": 4500,
    "presentations": 36000
  },
  {
    "name": "a016_th60",
    "params": {
      "n_exc": 800,
      "n_per_class": 450,
      "epochs": 8,
      "T": 350,
      "a_plus": 0.016,
      "a_minus": 0.012,
      "norm_target": 90.0,
      "w_inh": 0.6,
      "theta_plus": 0.6,
      "r_m": 6.0,
      "input_norm_power": 0.5,
      "batch": 128,
      "max_rate": 63.75
    },
    "acc": 0.4686666666666667,
    "tmpl_match": 0.2796276745096113,
    "tv": 1.3408054126054048,
    "dead": 0.04125,
    "cov_spread": 7.619047619047619,
    "n_zero_classes": 0,
    "sec": 1647.6464731693268,
    "n_train": 4500,
    "presentations": 36000
  },
  {
    "name": "a016_th80",
    "params": {
      "n_exc": 800,
      "n_per_class": 450,
      "epochs": 8,
      "T": 350,
      "a_plus": 0.016,
      "a_minus": 0.012,
      "norm_target": 90.0,
      "w_inh": 0.6,
      "theta_plus": 0.8,
      "r_m": 6.0,
      "input_norm_power": 0.5,
      "batch": 128,
      "max_rate": 63.75
    },
    "acc": 0.4693333333333333,
    "tmpl_match": 0.34748731144690453,
    "tv": 1.2938952464610338,
    "dead": 0.02125,
    "cov_spread": 5.448275862068965,
    "n_zero_classes": 0,
    "sec": 1646.3155727386475,
    "n_train": 4500,
    "presentations": 36000
  }
]